denet-0.4.2.dist-info/METADATA
denet-0.4.2.dist-info/WHEEL
denet-0.4.2.dist-info/licenses/LICENSE
denet/__init__.py
denet/_denet.cpython-312-x86_64-linux-gnu.so
denet/analysis.py
denet-0.4.2.dist-info/RECORD
