Metadata-Version: 2.4
Name: denet
Version: 0.4.2
Classifier: Development Status :: 3 - Alpha
Classifier: Programming Language :: Python :: 3
Classifier: Programming Language :: Python :: 3.12
Classifier: Programming Language :: Python :: 3.13
Classifier: Programming Language :: Rust
Classifier: License :: OSI Approved :: GNU General Public License v3 (GPLv3)
License-File: LICENSE
Summary: A streaming process monitoring tool
Keywords: profiling,monitor,cpu,resources
Home-Page: https://github.com/btraven00/denet
Author: btraven00
Author-email: ben <ben.uzh@proton.me>
License: GPL-3.0-or-later
Requires-Python: >=3.6
Project-URL: Source Code, https://github.com/btraven00/denet
